README
setup.py
v12/__init__.py
v12/buildsystem.py
v12/cachebuster.py
v12/cli.py
v12/environment.py
v12/packagemanager.py
v12/removeme.py
v12/routing.py
v12/utils.py
v12.egg-info/PKG-INFO
v12.egg-info/SOURCES.txt
v12.egg-info/dependency_links.txt
v12.egg-info/entry_points.txt
v12.egg-info/not-zip-safe
v12.egg-info/requires.txt
v12.egg-info/top_level.txt