Metadata-Version: 1.1
Name: v12
Version: 0.1.2dev
Summary: Google App Engine web framework built on webapp2
Home-page: http://github.com/rsimp/v12
Author: Robert Simpson
Author-email: robhsimpson@gmail.com
License: MIT
Keywords: gae web framework webapp2 command line cli google app engine appengine paas build system package manager routing routes scaffolding asset pipeline fingerprint cache buster cachebuster cachebusting
Platform: UNKNOWN
Classifier: Development Status :: 3 - Alpha
Classifier: License :: OSI Approved :: MIT License
Classifier: Programming Language :: Python :: 2.7
